{"id":1002,"url":"http://bgm.tv/subject/1002","type":2,"name":"KEY THE METAL IDOL","name_cn":"非常偶像Key","summary":"某日，正在上高中的巳真兔季子（KEY）突然接到了和自己相依为命的爷爷的死讯，但她却哭不出来，因为她是个“机器人”，一个由爷爷亲手创造的完美的“机器人”，也正是由于这一点她从小就一直受到周围同龄人的讥笑和嘲讽。爷爷死前给KEY留下了口信，“去吧，孩子，你不用再作为一个机器人活着，去成为一个真正的人......但有个条件，你必需要有朋友，真正的朋友，能全心全意为你哭、为你笑的人，人数大约需要三万人。”\r\n\r\n抱着这样一个几乎不可能实现的愿望，KEY只身来到东京。在这里她遇到了以前国中的朋友厨川樱，以及偶像歌星美浦的歌迷会会长三和土州一，大家一起为实现KEY的愿望，将她发展成偶像歌手而努力着。同时爷爷的助手若木知叶也悄悄来到了东京，似乎预示着KEY身边会发生不寻常的事。另一方面，偶像歌星美浦及其所属的米诺斯公司也并非看上去的那么简单，到底它的后台老板蛙杖有什么不可告人的目的？他与KEY爷爷的死有关吗？KEY的身体里到底有什么秘密？她最后能如愿地成为偶像，变成一个普通的女孩吗？","eps":[{"id":93101,"url":"http://bgm.tv/ep/93101","type":0,"sort":1,"name":"起動","name_cn":"","duration":"25m","airdate":"1994年12月16日","comment":1,"desc":"","status":"Air"},{"id":93102,"url":"http://bgm.tv/ep/93102","type":0,"sort":2,"name":"カーソルI","name_cn":"","duration":"25m","airdate":"1995年2月17日","comment":1,"desc":"","status":"Air"},{"id":93103,"url":"http://bgm.tv/ep/93103","type":0,"sort":3,"name":"カーソルII","name_cn":"","duration":"25m","airdate":"1995年3月1日","comment":1,"desc":"","status":"Air"},{"id":93104,"url":"http://bgm.tv/ep/93104","type":0,"sort":4,"name":"アクセス","name_cn":"","duration":"25m","airdate":"1995年4月5日","comment":1,"desc":"","status":"Air"},{"id":93105,"url":"http://bgm.tv/ep/93105","type":0,"sort":5,"name":"スクロールI","name_cn":"","duration":"25m","airdate":"1995年6月7日","comment":0,"desc":"","status":"Air"},{"id":93106,"url":"http://bgm.tv/ep/93106","type":0,"sort":6,"name":"スクロールII","name_cn":"","duration":"25m","airdate":"1995年7月5日","comment":0,"desc":"","status":"Air"},{"id":93107,"url":"http://bgm.tv/ep/93107","type":0,"sort":7,"name":"ラン","name_cn":"","duration":"25m","airdate":"1995年8月2日","comment":2,"desc":"","status":"Air"},{"id":93108,"url":"http://bgm.tv/ep/93108","type":0,"sort":8,"name":"ゴー・トゥ","name_cn":"","duration":"25m","airdate":"1996年2月7日","comment":1,"desc":"","status":"Air"},{"id":93109,"url":"http://bgm.tv/ep/93109","type":0,"sort":9,"name":"リターン","name_cn":"","duration":"25m","airdate":"1996年3月6日","comment":0,"desc":"","status":"Air"},{"id":93110,"url":"http://bgm.tv/ep/93110","type":0,"sort":10,"name":"バグ","name_cn":"","duration":"25m","airdate":"1996年4月3日","comment":0,"desc":"","status":"Air"},{"id":93111,"url":"http://bgm.tv/ep/93111","type":0,"sort":11,"name":"セーブ","name_cn":"","duration":"25m","airdate":"1996年5月2日","comment":0,"desc":"","status":"Air"},{"id":93112,"url":"http://bgm.tv/ep/93112","type":0,"sort":12,"name":"ヴァイラスI","name_cn":"","duration":"25m","airdate":"1996年7月3日","comment":0,"desc":"","status":"Air"},{"id":93113,"url":"http://bgm.tv/ep/93113","type":0,"sort":13,"name":"ヴァイラスII","name_cn":"","duration":"25m","airdate":"1996年8月7日","comment":1,"desc":"","status":"Air"},{"id":93114,"url":"http://bgm.tv/ep/93114","type":0,"sort":14,"name":"システム","name_cn":"","duration":"97m","airdate":"1997年3月21日","comment":3,"desc":"","status":"Air"},{"id":93115,"url":"http://bgm.tv/ep/93115","type":0,"sort":15,"name":"終了","name_cn":"","duration":"99m","airdate":"1997年6月18日","comment":1,"desc":"","status":"Air"}],"eps_count":15,"air_date":"1994-12-16","air_weekday":5,"rating":{"total":109,"count":{"1":1,"2":1,"3":1,"4":3,"5":9,"6":25,"7":33,"8":24,"9":9,"10":3},"score":6.9},"rank":2400,"images":{"large":"http://lain.bgm.tv/pic/cover/l/fb/a9/1002_4yBgv.jpg","common":"http://lain.bgm.tv/pic/cover/c/fb/a9/1002_4yBgv.jpg","medium":"http://lain.bgm.tv/pic/cover/m/fb/a9/1002_4yBgv.jpg","small":"http://lain.bgm.tv/pic/cover/s/fb/a9/1002_4yBgv.jpg","grid":"http://lain.bgm.tv/pic/cover/g/fb/a9/1002_4yBgv.jpg"},"collection":{"wish":221,"collect":142,"doing":19,"on_hold":22,"dropped":12},"crt":[{"id":19166,"url":"http://bgm.tv/character/19166","name":"巳真兎季子","name_cn":"巳真兔季子","role_name":"主角","images":{"large":"http://lain.bgm.tv/pic/crt/l/6f/c5/19166_crt_W6RR5.jpg?r=1362629748","medium":"http://lain.bgm.tv/pic/crt/m/6f/c5/19166_crt_W6RR5.jpg?r=1362629748","small":"http://lain.bgm.tv/pic/crt/s/6f/c5/19166_crt_W6RR5.jpg?r=1362629748","grid":"http://lain.bgm.tv/pic/crt/g/6f/c5/19166_crt_W6RR5.jpg?r=1362629748"},"comment":2,"collects":6,"info":{"name_cn":"巳真兔季子","alias":{"0":"KEY","en":"Tokiko Mima","jp":"巳真兎季子","kana":"みま・ときこ","nick":"key"},"gender":"女"},"actors":[{"id":3916,"url":"http://bgm.tv/person/3916","name":"岩男潤子","images":{"large":"http://lain.bgm.tv/pic/crt/l/2b/64/3916_prsn_5i7T7.jpg","medium":"http://lain.bgm.tv/pic/crt/m/2b/64/3916_prsn_5i7T7.jpg","small":"http://lain.bgm.tv/pic/crt/s/2b/64/3916_prsn_5i7T7.jpg","grid":"http://lain.bgm.tv/pic/crt/g/2b/64/3916_prsn_5i7T7.jpg"}}]},{"id":25067,"url":"http://bgm.tv/character/25067","name":"厨川さくら","name_cn":"厨川樱","role_name":"主角","images":{"large":"http://lain.bgm.tv/pic/crt/l/61/6a/25067_crt_H6xAi.jpg","medium":"http://lain.bgm.tv/pic/crt/m/61/6a/25067_crt_H6xAi.jpg","small":"http://lain.bgm.tv/pic/crt/s/61/6a/25067_crt_H6xAi.jpg","grid":"http://lain.bgm.tv/pic/crt/g/61/6a/25067_crt_H6xAi.jpg"},"comment":1,"collects":2,"info":{"name_cn":"厨川樱","alias":{"kana":"くりやがわ さくら","romaji":"Kuriyagawa Sakura"},"source":"anidb.net"},"actors":[{"id":3913,"url":"http://bgm.tv/person/3913","name":"長沢美樹","images":{"large":"http://lain.bgm.tv/pic/crt/l/7c/96/3913_prsn_LzOT6.jpg?r=1462917319","medium":"http://lain.bgm.tv/pic/crt/m/7c/96/3913_prsn_LzOT6.jpg?r=1462917319","small":"http://lain.bgm.tv/pic/crt/s/7c/96/3913_prsn_LzOT6.jpg?r=1462917319","grid":"http://lain.bgm.tv/pic/crt/g/7c/96/3913_prsn_LzOT6.jpg?r=1462917319"}}]}],"staff":[{"id":506,"url":"http://bgm.tv/person/506","name":"佐藤博暉","name_cn":"佐藤博晖","role_name":"","images":null,"comment":6,"collects":0,"info":{"name_cn":"佐藤博晖","alias":{"jp":"佐藤博暉","romaji":"Satou Hiroaki"},"gender":"男","birth":"1959-09-03"},"jobs":["原作","导演","脚本"]},{"id":12300,"url":"http://bgm.tv/person/12300","name":"松村将弘","name_cn":"","role_name":"","images":null,"comment":0,"collects":0,"info":null,"jobs":["脚本"]},{"id":502,"url":"http://bgm.tv/person/502","name":"うえだしげる","name_cn":"上田茂","role_name":"","images":null,"comment":1,"collects":0,"info":{"name_cn":"上田茂","alias":{"jp":"うえだしげる","romaji":"Ueda Shigeru"},"gender":"男"},"jobs":["分镜"]},{"id":918,"url":"http://bgm.tv/person/918","name":"山口頼房","name_cn":"山口赖房","role_name":"","images":null,"comment":0,"collects":0,"info":{"name_cn":"山口赖房","alias":{"0":"みなみ はるか","1":"山口よりふさ","kana":"やまぐち よりふさ","romaji":"Yamaguchi Yorichika"},"gender":"男","birth":"1959年"},"jobs":["分镜"]},{"id":172,"url":"http://bgm.tv/person/172","name":"渡部高志","name_cn":"渡部高志","role_name":"","images":{"large":"http://lain.bgm.tv/pic/crt/l/1f/f8/172_prsn_anidb.jpg","medium":"http://lain.bgm.tv/pic/crt/m/1f/f8/172_prsn_anidb.jpg","small":"http://lain.bgm.tv/pic/crt/s/1f/f8/172_prsn_anidb.jpg","grid":"http://lain.bgm.tv/pic/crt/g/1f/f8/172_prsn_anidb.jpg"},"comment":15,"collects":0,"info":{"name_cn":"渡部高志","alias":{"0":"河口もと","jp":"渡部高志","kana":"わたなべ たかし","romaji":"Watanabe Takashi"},"gender":"男","birth":"1957-07-22"},"jobs":["分镜"]},{"id":376,"url":"http://bgm.tv/person/376","name":"舛成孝二","name_cn":"舛成孝二","role_name":"","images":{"large":"http://lain.bgm.tv/pic/crt/l/64/03/376_prsn_taXZP.jpg?r=1442897886","medium":"http://lain.bgm.tv/pic/crt/m/64/03/376_prsn_taXZP.jpg?r=1442897886","small":"http://lain.bgm.tv/pic/crt/s/64/03/376_prsn_taXZP.jpg?r=1442897886","grid":"http://lain.bgm.tv/pic/crt/g/64/03/376_prsn_taXZP.jpg?r=1442897886"},"comment":2,"collects":0,"info":{"name_cn":"舛成孝二","alias":{"jp":"舛成孝二","kana":"ますなりこうじ","romaji":"Masunari Kouji"},"gender":"男","birth":"1965年1月1日"},"jobs":["分镜"]},{"id":1702,"url":"http://bgm.tv/person/1702","name":"近藤信宏","name_cn":"近藤信宏","role_name":"","images":null,"comment":0,"collects":0,"info":{"name_cn":"近藤信宏","alias":{"jp":"近藤信宏","kana":"こんどうのぶひろ","romaji":"Kondou Nobuhiro"},"gender":"男"},"jobs":["分镜"]}],"topic":[{"id":10356,"url":"http://bgm.tv/subject/topic/10356","title":"非常偶像Key的英配版现已加入B站视频！","main_id":1002,"timestamp":1474793099,"lastpost":1566780308,"replies":2,"user":{"id":228778,"url":"http://bgm.tv/user/228778","username":"228778","nickname":"岩仓玲音","avatar":{"large":"http://lain.bgm.tv/pic/user/l/000/22/87/228778.jpg?r=1451104492","medium":"http://lain.bgm.tv/pic/user/m/000/22/87/228778.jpg?r=1451104492","small":"http://lain.bgm.tv/pic/user/s/000/22/87/228778.jpg?r=1451104492"},"sign":null}},{"id":10250,"url":"http://bgm.tv/subject/topic/10250","title":"嘛","main_id":1002,"timestamp":1472186271,"lastpost":1472186271,"replies":0,"user":{"id":269858,"url":"http://bgm.tv/user/269858","username":"269858","nickname":"kotosaki","avatar":{"large":"http://lain.bgm.tv/pic/user/l/000/26/98/269858.jpg?r=1608485959","medium":"http://lain.bgm.tv/pic/user/m/000/26/98/269858.jpg?r=1608485959","small":"http://lain.bgm.tv/pic/user/s/000/26/98/269858.jpg?r=1608485959"},"sign":null}}],"blog":[{"id":282033,"url":"http://bgm.tv/blog/282033","title":"KEY THE METAL IDOL相关访谈（3）","summary":"这篇是在1994.12.16发布第一卷之前，无剧透的导演佐藤博晖一本正经胡说八道的日语访谈视频，我从英文字幕翻译了。\r\n\r\n问：KEY THE METAL IDOL是什么样的故事呢？\r\n答：Key是主角的名字。她是机器人。她和制造出她的爷爷一起住在小山村。爷爷离世之际给Key的遗言说，Key可以成 ...","image":"","replies":0,"timestamp":1538271630,"dateline":"2018-9-30 01:40","user":{"id":426892,"url":"http://bgm.tv/user/426892","username":"426892","nickname":"biry","avatar":{"large":"http://lain.bgm.tv/pic/user/l/000/42/68/426892.jpg?r=1589664635","medium":"http://lain.bgm.tv/pic/user/m/000/42/68/426892.jpg?r=1589664635","small":"http://lain.bgm.tv/pic/user/s/000/42/68/426892.jpg?r=1589664635"},"sign":null}},{"id":282032,"url":"http://bgm.tv/blog/282032","title":"KEY THE METAL IDOL相关访谈（2）","summary":"这篇FAQ同样包含剧透。\r\n\r\nFrequently Asked Questions\r\nDirector Sato's answers to questions about Key the Metal Idol\r\n\r\nQ: What's the difference between the &quot;Sipe&quot; and the PPOR?\r\nA: The &quot;Sipe&quot; and PPOR are the same thing. Ajo's staff has nicknamed  ...","image":"","replies":0,"timestamp":1538269424,"dateline":"2018-9-30 01:03","user":{"id":426892,"url":"http://bgm.tv/user/426892","username":"426892","nickname":"biry","avatar":{"large":"http://lain.bgm.tv/pic/user/l/000/42/68/426892.jpg?r=1589664635","medium":"http://lain.bgm.tv/pic/user/m/000/42/68/426892.jpg?r=1589664635","small":"http://lain.bgm.tv/pic/user/s/000/42/68/426892.jpg?r=1589664635"},"sign":null}},{"id":282031,"url":"http://bgm.tv/blog/282031","title":"KEY THE METAL IDOL相关访谈（1）","summary":"搬运自图片和视频资源。有一定程度的剧透。Viz版本的DVD里面收录了月刊Animerica的若干专访，不过我只收集到大约三分之一的内容。\r\n\r\nInterview with the Director: Part 1\r\nANIMERICA INTERVIEW WITH HIROAKI SATO\r\n\r\nAnimerica: What was the road that Key took t ...","image":"","replies":0,"timestamp":1538267706,"dateline":"2018-9-30 00:35","user":{"id":426892,"url":"http://bgm.tv/user/426892","username":"426892","nickname":"biry","avatar":{"large":"http://lain.bgm.tv/pic/user/l/000/42/68/426892.jpg?r=1589664635","medium":"http://lain.bgm.tv/pic/user/m/000/42/68/426892.jpg?r=1589664635","small":"http://lain.bgm.tv/pic/user/s/000/42/68/426892.jpg?r=1589664635"},"sign":null}},{"id":273035,"url":"http://bgm.tv/blog/273035","title":"[补旧番]非常偶像key——20年前的另类黑暗偶像动画","summary":"带图原文地址http://www.acgpiping.net/2016/6327/key-the-metal-idol/\r\n\r\n最近补了一部20年前的偶像动画《非常偶像key》，一句话来介绍这部动画的话大概就是“以EVA的风格来拍一部偶像动画是怎样一种体验”，大概20年前的动画都不喜欢好好讲故事吧。先摘抄一段wiki ...","image":"","replies":0,"timestamp":1463896703,"dateline":"2016-5-22 05:58","user":{"id":2195,"url":"http://bgm.tv/user/windchaos","username":"windchaos","nickname":"windchaos","avatar":{"large":"http://lain.bgm.tv/pic/user/l/000/00/21/2195.jpg","medium":"http://lain.bgm.tv/pic/user/m/000/00/21/2195.jpg","small":"http://lain.bgm.tv/pic/user/s/000/00/21/2195.jpg"},"sign":null}}]}