{"id":10407,"url":"http://bgm.tv/subject/10407","type":2,"name":"ミスター味っ子","name_cn":"妙手小厨师","summary":"主角味吉阳一继承了父亲留下来的大众食堂，在机缘巧合下认识了厨师协会的统帅，人称「味皇」的村田源二郎，更被味皇选中担任味皇料理某部门的主任……接受各人各项的美味比赛……最后阳一又能否胜任？「肚子饿的时候，什么也做不来，不能应战，也不能画漫画。不管是你，还是我，大家都喜欢吃，但既然要吃，还是要挑好吃的。因此，请大家好好享受一下阳一所设计出来的满分料理吧！","eps":99,"eps_count":99,"air_date":"1987-10-08","air_weekday":4,"rating":{"total":36,"count":{"1":0,"2":0,"3":0,"4":0,"5":1,"6":8,"7":10,"8":12,"9":2,"10":3},"score":7.4},"images":{"large":"http://lain.bgm.tv/pic/cover/l/a8/78/10407_P0t08.jpg","common":"http://lain.bgm.tv/pic/cover/c/a8/78/10407_P0t08.jpg","medium":"http://lain.bgm.tv/pic/cover/m/a8/78/10407_P0t08.jpg","small":"http://lain.bgm.tv/pic/cover/s/a8/78/10407_P0t08.jpg","grid":"http://lain.bgm.tv/pic/cover/g/a8/78/10407_P0t08.jpg"},"collection":{"wish":26,"collect":56,"doing":10,"on_hold":8,"dropped":7}}