{"id":219568,"url":"http://bgm.tv/subject/219568","type":2,"name":"博多豚骨ラーメンズ","name_cn":"博多豚骨拉面","summary":"“你无论如何都有想要杀掉的人，无论怎样都想要杀人吗。”\r\n福冈是个外表看起来很和平的城市，但暗中却蔓延着犯罪。如今在杀手行业的激战区，存在着专以杀手为目标的杀手——甚至出现了这样的都市传说。\r\n杀手、侦探、复仇代理人、情报商、拷问师etc——，从事黑暗行业的男人们的故事编织而成之时，“专杀杀手的杀手”现身了——。","eps":12,"eps_count":12,"air_date":"2018-01-12","air_weekday":5,"rating":{"total":2196,"count":{"1":7,"2":6,"3":18,"4":60,"5":180,"6":702,"7":852,"8":333,"9":24,"10":14},"score":6.6},"rank":4171,"images":{"large":"http://lain.bgm.tv/pic/cover/l/bd/cd/219568_Z44lz.jpg","common":"http://lain.bgm.tv/pic/cover/c/bd/cd/219568_Z44lz.jpg","medium":"http://lain.bgm.tv/pic/cover/m/bd/cd/219568_Z44lz.jpg","small":"http://lain.bgm.tv/pic/cover/s/bd/cd/219568_Z44lz.jpg","grid":"http://lain.bgm.tv/pic/cover/g/bd/cd/219568_Z44lz.jpg"},"collection":{"wish":416,"collect":2923,"doing":257,"on_hold":235,"dropped":323}}