{"id":231971,"url":"http://bgm.tv/subject/231971","type":2,"name":"ベイブレード バースト 超ゼツ","name_cn":"霸旋陀螺 爆刃对决 超Z","summary":"赤刃アイガは豊かな自然の中で育った超野性児。\r\n世界チャンピオン蒼井バルトとのベイバトルに刺激を受けたアイガは、\r\n超ゼツベイ・ゼットアキレスと共に\r\n最強無敵のブレーダーを目指すようになる。\r\nもっと強い相手と戦って、もっと強くなりたい。\r\nアイガは、世界タイトルマッチの挑戦権を得てバルトを倒すために、\r\n世界へと飛び出す。\r\n\r\n今ここに赤刃アイガの\r\n冒険と挑戦の日々が始まる。","eps":51,"eps_count":51,"air_date":"2018-04-02","air_weekday":1,"rating":{"total":3,"count":{"1":0,"2":0,"3":0,"4":0,"5":1,"6":1,"7":0,"8":1,"9":0,"10":0},"score":6.3},"images":{"large":"http://lain.bgm.tv/pic/cover/l/28/c2/231971_eAn8a.jpg","common":"http://lain.bgm.tv/pic/cover/c/28/c2/231971_eAn8a.jpg","medium":"http://lain.bgm.tv/pic/cover/m/28/c2/231971_eAn8a.jpg","small":"http://lain.bgm.tv/pic/cover/s/28/c2/231971_eAn8a.jpg","grid":"http://lain.bgm.tv/pic/cover/g/28/c2/231971_eAn8a.jpg"},"collection":{"wish":7,"collect":7,"on_hold":1,"dropped":9}}