{"id":285482,"url":"http://bgm.tv/subject/285482","type":2,"name":"異種族レビュアーズ","name_cn":"异种族风俗娘评鉴指南","summary":"ここは人間だけではなく、エルフ、獣人、悪魔に天使と、あらゆる異種族が混在し、暮らしている世界。そこには当然、あらゆる異種族のスケベなお店もあるわけで…。\r\n\r\n足しげくムフフなサービスをしてくれるお店に通う人間の冒険者・スタンクは、ある日種族間の（性的な意味での）感性の違いで悪友のエロエルフ・ゼルと衝突する。\r\n\r\n決着の方法は……嬢のレビュー!?　あらゆる異種族娘のサービスをクロスレビュー方式で採点し、他の仲間達への“お役勃ち”情報として提供していくスタンクたちの活躍は、まさに性戦士のごとし！\r\n\r\n今日もレビュアーズたちは新たな快楽を求めて旅勃って行く……。","eps":12,"eps_count":12,"air_date":"2020-01-11","air_weekday":6,"rating":{"total":4552,"count":{"1":10,"2":6,"3":9,"4":30,"5":90,"6":320,"7":1120,"8":2027,"9":634,"10":306},"score":7.8},"rank":432,"images":{"large":"http://lain.bgm.tv/pic/cover/l/dc/8a/285482_c5RRj.jpg","common":"http://lain.bgm.tv/pic/cover/c/dc/8a/285482_c5RRj.jpg","medium":"http://lain.bgm.tv/pic/cover/m/dc/8a/285482_c5RRj.jpg","small":"http://lain.bgm.tv/pic/cover/s/dc/8a/285482_c5RRj.jpg","grid":"http://lain.bgm.tv/pic/cover/g/dc/8a/285482_c5RRj.jpg"},"collection":{"wish":1008,"collect":5752,"doing":795,"on_hold":310,"dropped":174}}