{"id":321092,"url":"http://bgm.tv/subject/321092","type":2,"name":"闇芝居 第8期","name_cn":"暗芝居 第八季","summary":"","air_date":"2021-01-10","air_weekday":7,"rating":{"total":1,"count":{"1":0,"2":0,"3":0,"4":0,"5":1,"6":0,"7":0,"8":0,"9":0,"10":0},"score":5},"images":{"large":"http://lain.bgm.tv/pic/cover/l/29/51/321092_yFId5.jpg","common":"http://lain.bgm.tv/pic/cover/c/29/51/321092_yFId5.jpg","medium":"http://lain.bgm.tv/pic/cover/m/29/51/321092_yFId5.jpg","small":"http://lain.bgm.tv/pic/cover/s/29/51/321092_yFId5.jpg","grid":"http://lain.bgm.tv/pic/cover/g/29/51/321092_yFId5.jpg"},"collection":{"wish":13,"doing":30,"on_hold":1,"dropped":4},"crt":null,"staff":null,"eps":[{"id":1001072,"url":"http://bgm.tv/ep/1001072","type":0,"sort":1,"name":"","name_cn":"","duration":"","airdate":"","comment":2,"desc":"","status":"Air"},{"id":1001073,"url":"http://bgm.tv/ep/1001073","type":0,"sort":2,"name":"","name_cn":"","duration":"","airdate":"","comment":0,"desc":"","status":"Air"},{"id":1001074,"url":"http://bgm.tv/ep/1001074","type":0,"sort":3,"name":"","name_cn":"","duration":"","airdate":"","comment":0,"desc":"","status":"Air"},{"id":1001075,"url":"http://bgm.tv/ep/1001075","type":0,"sort":4,"name":"","name_cn":"","duration":"","airdate":"","comment":0,"desc":"","status":"Air"},{"id":1001076,"url":"http://bgm.tv/ep/1001076","type":0,"sort":5,"name":"","name_cn":"","duration":"","airdate":"","comment":0,"desc":"","status":"Air"},{"id":1001077,"url":"http://bgm.tv/ep/1001077","type":0,"sort":6,"name":"","name_cn":"","duration":"","airdate":"","comment":0,"desc":"","status":"Air"},{"id":1001078,"url":"http://bgm.tv/ep/1001078","type":0,"sort":7,"name":"","name_cn":"","duration":"","airdate":"","comment":0,"desc":"","status":"Air"},{"id":1001079,"url":"http://bgm.tv/ep/1001079","type":0,"sort":8,"name":"","name_cn":"","duration":"","airdate":"","comment":0,"desc":"","status":"Air"},{"id":1001080,"url":"http://bgm.tv/ep/1001080","type":0,"sort":9,"name":"","name_cn":"","duration":"","airdate":"","comment":0,"desc":"","status":"Air"},{"id":1001081,"url":"http://bgm.tv/ep/1001081","type":0,"sort":10,"name":"","name_cn":"","duration":"","airdate":"","comment":0,"desc":"","status":"Air"},{"id":1001082,"url":"http://bgm.tv/ep/1001082","type":0,"sort":11,"name":"","name_cn":"","duration":"","airdate":"","comment":0,"desc":"","status":"Air"}],"topic":null,"blog":null}