{"id":3485,"url":"http://bgm.tv/subject/3485","type":2,"name":"魔法少女リリカルなのは The MOVIE 1st","name_cn":"魔法少女奈叶 The MOVIE 1st","summary":"剧场版「魔法少女奈叶 The MOVIE 1st」是动画第一季「魔法少女奈叶」的升级强化版。将TV系列第1季全13话的映像进行组合，制作成超过100分钟的新映像作品，所以并不是通常所说的总集篇。故事既将忠实的跟随着第一季的线路，又会加入各种的展开（包括小说，DRAMA CD，续篇的附加设定）。对于看过TV系列的人来说，是触及对之后各种各样的事件而成长的，不知不觉成为引导新时代的两个少女，高町奈叶和菲特泰斯特罗莎的相遇和开端的故事；而对于第一次接触剧场的人来说这是个被命运翻弄的二个少女的相遇，战斗和友情的故事。满载SF风味的魔法战斗的视觉享受和直接的故事，以剧场版才有的质量展开。","eps":[{"id":306837,"url":"http://bgm.tv/ep/306837","type":0,"sort":1,"name":"魔法少女リリカルなのは The MOVIE 1st","name_cn":"魔法少女奈叶 The MOVIE 1st","duration":"","airdate":"","comment":3,"desc":"","status":"Air"}],"eps_count":1,"air_date":"2010-01-23","air_weekday":6,"rating":{"total":1292,"count":{"1":4,"2":1,"3":3,"4":3,"5":26,"6":117,"7":402,"8":514,"9":154,"10":68},"score":7.6},"rank":629,"images":{"large":"http://lain.bgm.tv/pic/cover/l/df/eb/3485_YG3XR.jpg","common":"http://lain.bgm.tv/pic/cover/c/df/eb/3485_YG3XR.jpg","medium":"http://lain.bgm.tv/pic/cover/m/df/eb/3485_YG3XR.jpg","small":"http://lain.bgm.tv/pic/cover/s/df/eb/3485_YG3XR.jpg","grid":"http://lain.bgm.tv/pic/cover/g/df/eb/3485_YG3XR.jpg"},"collection":{"wish":309,"collect":1905,"doing":14,"on_hold":68,"dropped":33},"crt":[{"id":2782,"url":"http://bgm.tv/character/2782","name":"高町なのは","name_cn":"高町奈叶","role_name":"主角","images":{"large":"http://lain.bgm.tv/pic/crt/l/f1/52/2782_crt_9fAi0.jpg?r=1472814152","medium":"http://lain.bgm.tv/pic/crt/m/f1/52/2782_crt_9fAi0.jpg?r=1472814152","small":"http://lain.bgm.tv/pic/crt/s/f1/52/2782_crt_9fAi0.jpg?r=1472814152","grid":"http://lain.bgm.tv/pic/crt/g/f1/52/2782_crt_9fAi0.jpg?r=1472814152"},"comment":31,"collects":155,"info":{"name_cn":"高町奈叶","alias":{"0":"管理局の白い悪魔","1":"白色恶魔","zh":"高町奈葉","en":"Nanoha Takamachi","jp":"高町なのは","kana":"たかまち なのは","romaji":"Takamachi Nanoha","nick":"暴君"},"gender":"女","birth":"0056年3月15日（三角心）","bloodtype":"O型（三角心）","height":"129cm（三角心）、135cm→160cm","weight":"24kg（三角心）","学校":"私立聖祥大附属小学校"},"actors":[{"id":3965,"url":"http://bgm.tv/person/3965","name":"田村ゆかり","images":{"large":"http://lain.bgm.tv/pic/crt/l/95/82/3965_prsn_f6OQk.jpg?r=1531553406","medium":"http://lain.bgm.tv/pic/crt/m/95/82/3965_prsn_f6OQk.jpg?r=1531553406","small":"http://lain.bgm.tv/pic/crt/s/95/82/3965_prsn_f6OQk.jpg?r=1531553406","grid":"http://lain.bgm.tv/pic/crt/g/95/82/3965_prsn_f6OQk.jpg?r=1531553406"}}]},{"id":2792,"url":"http://bgm.tv/character/2792","name":"フェイト・テスタロッサ","name_cn":"菲特·泰斯特罗莎","role_name":"主角","images":{"large":"http://lain.bgm.tv/pic/crt/l/f5/e0/2792_crt_qDcaH.jpg?r=1559754207","medium":"http://lain.bgm.tv/pic/crt/m/f5/e0/2792_crt_qDcaH.jpg?r=1559754207","small":"http://lain.bgm.tv/pic/crt/s/f5/e0/2792_crt_qDcaH.jpg?r=1559754207","grid":"http://lain.bgm.tv/pic/crt/g/f5/e0/2792_crt_qDcaH.jpg?r=1559754207"},"comment":8,"collects":156,"info":{"name_cn":"菲特·泰斯特罗莎","alias":{"0":"菲特·泰斯特罗莎·哈拉温","1":"菲特·泰斯塔罗莎·哈拉温","2":"フェイト・テスタロッサ・ハラオウン","3":"Fate T. Harlaown","zh":"菲特·T·哈拉温","en":"Fate Testarossa Harlaown","jp":"フェイト・T・テスタロッサ","romaji":"Feito Tesutarossa Haraoun","nick":"菲特、宠妃"},"gender":"女","height":"137cm/164cm","source":"anidb.net","学校":"私立聖祥大附属小学校"},"actors":[{"id":1,"url":"http://bgm.tv/person/1","name":"水樹奈々","images":{"large":"http://lain.bgm.tv/pic/crt/l/a6/e8/1_prsn_ZdFfp.jpg?r=1597241889","medium":"http://lain.bgm.tv/pic/crt/m/a6/e8/1_prsn_ZdFfp.jpg?r=1597241889","small":"http://lain.bgm.tv/pic/crt/s/a6/e8/1_prsn_ZdFfp.jpg?r=1597241889","grid":"http://lain.bgm.tv/pic/crt/g/a6/e8/1_prsn_ZdFfp.jpg?r=1597241889"}}]},{"id":3740,"url":"http://bgm.tv/character/3740","name":"ユーノ・スクライア","name_cn":"尤诺·斯克莱亚","role_name":"配角","images":{"large":"http://lain.bgm.tv/pic/crt/l/33/ef/3740_crt_anidb.jpg?r=1399740618","medium":"http://lain.bgm.tv/pic/crt/m/33/ef/3740_crt_anidb.jpg?r=1399740618","small":"http://lain.bgm.tv/pic/crt/s/33/ef/3740_crt_anidb.jpg?r=1399740618","grid":"http://lain.bgm.tv/pic/crt/g/33/ef/3740_crt_anidb.jpg?r=1399740618"},"comment":7,"collects":7,"info":{"name_cn":"尤诺·斯克莱亚","alias":{"jp":"ユーノ・スクライア","romaji":"Yuuno Scrya"},"gender":"男","source":"anidb.net"},"actors":[{"id":3851,"url":"http://bgm.tv/person/3851","name":"水橋かおり","images":{"large":"http://lain.bgm.tv/pic/crt/l/d1/01/3851_prsn_V23VU.jpg?r=1500667711","medium":"http://lain.bgm.tv/pic/crt/m/d1/01/3851_prsn_V23VU.jpg?r=1500667711","small":"http://lain.bgm.tv/pic/crt/s/d1/01/3851_prsn_V23VU.jpg?r=1500667711","grid":"http://lain.bgm.tv/pic/crt/g/d1/01/3851_prsn_V23VU.jpg?r=1500667711"}}]},{"id":19853,"url":"http://bgm.tv/character/19853","name":"アルフ","name_cn":"艾尔芙","role_name":"配角","images":{"large":"http://lain.bgm.tv/pic/crt/l/de/36/19853_crt_qPCH8.jpg","medium":"http://lain.bgm.tv/pic/crt/m/de/36/19853_crt_qPCH8.jpg","small":"http://lain.bgm.tv/pic/crt/s/de/36/19853_crt_qPCH8.jpg","grid":"http://lain.bgm.tv/pic/crt/g/de/36/19853_crt_qPCH8.jpg"},"comment":0,"collects":6,"info":{"name_cn":"艾尔芙","alias":{"en":"Arf","romaji":"Arufu"},"gender":"女"},"actors":[{"id":4168,"url":"http://bgm.tv/person/4168","name":"桑谷夏子","images":{"large":"http://lain.bgm.tv/pic/crt/l/0d/b1/4168_prsn_QjUU4.jpg?r=1507394630","medium":"http://lain.bgm.tv/pic/crt/m/0d/b1/4168_prsn_QjUU4.jpg?r=1507394630","small":"http://lain.bgm.tv/pic/crt/s/0d/b1/4168_prsn_QjUU4.jpg?r=1507394630","grid":"http://lain.bgm.tv/pic/crt/g/0d/b1/4168_prsn_QjUU4.jpg?r=1507394630"}}]},{"id":20100,"url":"http://bgm.tv/character/20100","name":"プレシア・テスタロッサ","name_cn":"普蕾茜亚·泰斯特罗莎","role_name":"配角","images":{"large":"http://lain.bgm.tv/pic/crt/l/3a/d7/20100_crt_Vc044.jpg","medium":"http://lain.bgm.tv/pic/crt/m/3a/d7/20100_crt_Vc044.jpg","small":"http://lain.bgm.tv/pic/crt/s/3a/d7/20100_crt_Vc044.jpg","grid":"http://lain.bgm.tv/pic/crt/g/3a/d7/20100_crt_Vc044.jpg"},"comment":0,"collects":1,"info":{"name_cn":"普蕾茜亚·泰斯特罗莎","alias":{"zh":"普蕾希亚·特斯塔萝莎","en":"Precia Testarossa","romaji":"Pureshia Tesutarossa"},"gender":"女"},"actors":[{"id":4053,"url":"http://bgm.tv/person/4053","name":"五十嵐麗","images":{"large":"http://lain.bgm.tv/pic/crt/l/95/65/4053_seiyu_anidb.jpg","medium":"http://lain.bgm.tv/pic/crt/m/95/65/4053_seiyu_anidb.jpg","small":"http://lain.bgm.tv/pic/crt/s/95/65/4053_seiyu_anidb.jpg","grid":"http://lain.bgm.tv/pic/crt/g/95/65/4053_seiyu_anidb.jpg"}}]},{"id":20101,"url":"http://bgm.tv/character/20101","name":"アリシア・テスタロッサ","name_cn":"艾丽茜亚·泰斯特罗莎","role_name":"配角","images":{"large":"http://lain.bgm.tv/pic/crt/l/a8/03/20101_crt_hd6qv.jpg","medium":"http://lain.bgm.tv/pic/crt/m/a8/03/20101_crt_hd6qv.jpg","small":"http://lain.bgm.tv/pic/crt/s/a8/03/20101_crt_hd6qv.jpg","grid":"http://lain.bgm.tv/pic/crt/g/a8/03/20101_crt_hd6qv.jpg"},"comment":4,"collects":5,"info":{"name_cn":"艾丽茜亚·泰斯特罗莎","alias":{"zh":"阿哩希亚·特斯塔萝莎","en":"Alicia Testarossa","romaji":"Arishia Tesutarossa"},"gender":"女"},"actors":[{"id":1,"url":"http://bgm.tv/person/1","name":"水樹奈々","images":{"large":"http://lain.bgm.tv/pic/crt/l/a6/e8/1_prsn_ZdFfp.jpg?r=1597241889","medium":"http://lain.bgm.tv/pic/crt/m/a6/e8/1_prsn_ZdFfp.jpg?r=1597241889","small":"http://lain.bgm.tv/pic/crt/s/a6/e8/1_prsn_ZdFfp.jpg?r=1597241889","grid":"http://lain.bgm.tv/pic/crt/g/a6/e8/1_prsn_ZdFfp.jpg?r=1597241889"}}]},{"id":3753,"url":"http://bgm.tv/character/3753","name":"リンディ・ハラオウン","name_cn":"琳蒂·哈洛温","role_name":"配角","images":{"large":"http://lain.bgm.tv/pic/crt/l/25/8e/3753_crt_anidb.jpg?r=1400341234","medium":"http://lain.bgm.tv/pic/crt/m/25/8e/3753_crt_anidb.jpg?r=1400341234","small":"http://lain.bgm.tv/pic/crt/s/25/8e/3753_crt_anidb.jpg?r=1400341234","grid":"http://lain.bgm.tv/pic/crt/g/25/8e/3753_crt_anidb.jpg?r=1400341234"},"comment":1,"collects":7,"info":{"name_cn":"琳蒂·哈洛温","alias":{"en":"Lindy Harlaown","jp":"リンディ・ハラオウン","romaji":"Rindi Haraoun"},"gender":"女","source":"anidb.net"},"actors":[{"id":3875,"url":"http://bgm.tv/person/3875","name":"久川綾","images":{"large":"http://lain.bgm.tv/pic/crt/l/a4/31/3875_prsn_AgpVo.jpg?r=1617907711","medium":"http://lain.bgm.tv/pic/crt/m/a4/31/3875_prsn_AgpVo.jpg?r=1617907711","small":"http://lain.bgm.tv/pic/crt/s/a4/31/3875_prsn_AgpVo.jpg?r=1617907711","grid":"http://lain.bgm.tv/pic/crt/g/a4/31/3875_prsn_AgpVo.jpg?r=1617907711"}}]},{"id":3743,"url":"http://bgm.tv/character/3743","name":"クロノ・ハラオウン","name_cn":"克洛诺·哈洛温","role_name":"配角","images":{"large":"http://lain.bgm.tv/pic/crt/l/1f/26/3743_crt_X0f0P.jpg?r=1445756920","medium":"http://lain.bgm.tv/pic/crt/m/1f/26/3743_crt_X0f0P.jpg?r=1445756920","small":"http://lain.bgm.tv/pic/crt/s/1f/26/3743_crt_X0f0P.jpg?r=1445756920","grid":"http://lain.bgm.tv/pic/crt/g/1f/26/3743_crt_X0f0P.jpg?r=1445756920"},"comment":1,"collects":4,"info":{"name_cn":"克洛诺·哈洛温","alias":{"en":"Chrono Harlaown","jp":"クロノ・ハラオウン","romaji":"Kurono Haraoun"},"gender":"男","source":"anidb.net"},"actors":[{"id":4412,"url":"http://bgm.tv/person/4412","name":"高橋美佳子","images":{"large":"http://lain.bgm.tv/pic/crt/l/c2/4f/4412_prsn_93P16.jpg?r=1400108998","medium":"http://lain.bgm.tv/pic/crt/m/c2/4f/4412_prsn_93P16.jpg?r=1400108998","small":"http://lain.bgm.tv/pic/crt/s/c2/4f/4412_prsn_93P16.jpg?r=1400108998","grid":"http://lain.bgm.tv/pic/crt/g/c2/4f/4412_prsn_93P16.jpg?r=1400108998"}}]},{"id":8825,"url":"http://bgm.tv/character/8825","name":"アリサ・バニングス","name_cn":"爱丽莎·巴尼斯","role_name":"配角","images":{"large":"http://lain.bgm.tv/pic/crt/l/77/65/8825_crt_648xV.jpg?r=1559987583","medium":"http://lain.bgm.tv/pic/crt/m/77/65/8825_crt_648xV.jpg?r=1559987583","small":"http://lain.bgm.tv/pic/crt/s/77/65/8825_crt_648xV.jpg?r=1559987583","grid":"http://lain.bgm.tv/pic/crt/g/77/65/8825_crt_648xV.jpg?r=1559987583"},"comment":3,"collects":5,"info":{"name_cn":"爱丽莎·巴尼斯","alias":{"zh":"亚莉莎·巴宁斯","en":"Alisa Bannings","romaji":"Arisa Baningusu"},"gender":"女"},"actors":[{"id":3936,"url":"http://bgm.tv/person/3936","name":"釘宮理恵","images":{"large":"http://lain.bgm.tv/pic/crt/l/24/4e/3936_prsn_XCuXF.jpg?r=1608682611","medium":"http://lain.bgm.tv/pic/crt/m/24/4e/3936_prsn_XCuXF.jpg?r=1608682611","small":"http://lain.bgm.tv/pic/crt/s/24/4e/3936_prsn_XCuXF.jpg?r=1608682611","grid":"http://lain.bgm.tv/pic/crt/g/24/4e/3936_prsn_XCuXF.jpg?r=1608682611"}}]}],"staff":[{"id":1414,"url":"http://bgm.tv/person/1414","name":"都築真紀","name_cn":"都筑真纪","role_name":"","images":{"large":"http://lain.bgm.tv/pic/crt/l/23/89/1414_prsn_M3c79.jpg?r=1560133245","medium":"http://lain.bgm.tv/pic/crt/m/23/89/1414_prsn_M3c79.jpg?r=1560133245","small":"http://lain.bgm.tv/pic/crt/s/23/89/1414_prsn_M3c79.jpg?r=1560133245","grid":"http://lain.bgm.tv/pic/crt/g/23/89/1414_prsn_M3c79.jpg?r=1560133245"},"comment":8,"collects":0,"info":{"name_cn":"都筑真纪","alias":{"zh":"毒株","jp":"都築真紀","kana":"つづき まさき","romaji":"Tsuzuki Masaki"},"gender":"男","birth":"2月16日","官网":"http://homepage1.nifty.com/tuz/"},"jobs":["原作","脚本"]},{"id":2913,"url":"http://bgm.tv/person/2913","name":"草川啓造","name_cn":"草川启造","role_name":"","images":{"large":"http://lain.bgm.tv/pic/crt/l/b3/1d/2913_prsn_anidb.jpg?r=1492444507","medium":"http://lain.bgm.tv/pic/crt/m/b3/1d/2913_prsn_anidb.jpg?r=1492444507","small":"http://lain.bgm.tv/pic/crt/s/b3/1d/2913_prsn_anidb.jpg?r=1492444507","grid":"http://lain.bgm.tv/pic/crt/g/b3/1d/2913_prsn_anidb.jpg?r=1492444507"},"comment":29,"collects":0,"info":{"name_cn":"草川启造","alias":{"0":"小唐子紋次郎","kana":"くさかわ けいぞう","romaji":"Kusakawa Keizou"},"gender":"男"},"jobs":["导演","分镜"]},{"id":306,"url":"http://bgm.tv/person/306","name":"坂田純一","name_cn":"坂田纯一","role_name":"","images":null,"comment":0,"collects":0,"info":{"name_cn":"坂田纯一","alias":{"kana":"さかた じゅんいち","romaji":"Sakata Jun`ichi"},"gender":"男"},"jobs":["分镜"]},{"id":11661,"url":"http://bgm.tv/person/11661","name":"宮澤努","name_cn":"宫泽努","role_name":"","images":null,"comment":1,"collects":0,"info":{"name_cn":"宫泽努","alias":{"0":"武藤技闇","kana":"みやざわ つとむ"}},"jobs":["分镜"]},{"id":621,"url":"http://bgm.tv/person/621","name":"まついひとゆき","name_cn":"松井仁之","role_name":"","images":{"large":"http://lain.bgm.tv/pic/crt/l/65/79/621_prsn_CK43q.jpg","medium":"http://lain.bgm.tv/pic/crt/m/65/79/621_prsn_CK43q.jpg","small":"http://lain.bgm.tv/pic/crt/s/65/79/621_prsn_CK43q.jpg","grid":"http://lain.bgm.tv/pic/crt/g/65/79/621_prsn_CK43q.jpg"},"comment":0,"collects":0,"info":{"name_cn":"松井仁之","alias":{"kana":"まつい ひとゆき","romaji":"Matsui Hitoyuki"},"gender":"男"},"jobs":["分镜"]},{"id":1144,"url":"http://bgm.tv/person/1144","name":"大森英敏","name_cn":"大森英敏","role_name":"","images":{"large":"http://lain.bgm.tv/pic/crt/l/45/88/1144_prsn_anidb.jpg","medium":"http://lain.bgm.tv/pic/crt/m/45/88/1144_prsn_anidb.jpg","small":"http://lain.bgm.tv/pic/crt/s/45/88/1144_prsn_anidb.jpg","grid":"http://lain.bgm.tv/pic/crt/g/45/88/1144_prsn_anidb.jpg"},"comment":1,"collects":0,"info":{"name_cn":"大森英敏","alias":{"0":"金剛寺弾","jp":"大森英敏","kana":"おおもり ひでとし","romaji":"Oomori Hidetoshi"},"gender":"男","birth":"1959年11月5日"},"jobs":["分镜"]},{"id":2076,"url":"http://bgm.tv/person/2076","name":"岩井優器","name_cn":"岩井优器","role_name":"","images":null,"comment":0,"collects":0,"info":{"name_cn":"岩井优器","alias":{"kana":"いわい ゆうき","romaji":"Iwai Yuuki"},"gender":"男"},"jobs":["分镜"]}],"topic":[{"id":848,"url":"http://bgm.tv/subject/topic/848","title":"强烈推荐补一下MOVIE 1st的漫画","main_id":3485,"timestamp":1291031377,"lastpost":1291040292,"replies":1,"user":{"id":3811,"url":"http://bgm.tv/user/kane","username":"kane","nickname":"Kane","avatar":{"large":"http://lain.bgm.tv/pic/user/l/000/00/38/3811.jpg?r=1336881427","medium":"http://lain.bgm.tv/pic/user/m/000/00/38/3811.jpg?r=1336881427","small":"http://lain.bgm.tv/pic/user/s/000/00/38/3811.jpg?r=1336881427"},"sign":null}}],"blog":[{"id":298516,"url":"http://bgm.tv/blog/298516","title":"10 Years - 2010","summary":"应群友要求写个2010-2020的年总，想了想临开学还有个把星期，闲着也是闲着，遂动笔。\r\n\r\n2010-怀旧与创新\r\n\r\n2009年是公认的业界传奇的一年，那一年有痞子的EVA，有同步完结的钢炼FA，有新房的物语，有京都的KON和09凉宫，有天麻，有炮姐，有鬼父，还有Mikufans。而随后的10年，作为21世纪 ...","image":"","replies":4,"timestamp":1598896583,"dateline":"2020-8-31 17:56","user":{"id":316039,"url":"http://bgm.tv/user/akaisuisei","username":"akaisuisei","nickname":"番组×幡具√","avatar":{"large":"http://lain.bgm.tv/pic/user/l/000/31/60/316039.jpg?r=1568007883","medium":"http://lain.bgm.tv/pic/user/m/000/31/60/316039.jpg?r=1568007883","small":"http://lain.bgm.tv/pic/user/s/000/31/60/316039.jpg?r=1568007883"},"sign":null}}]}