{"id":37673,"url":"http://bgm.tv/subject/37673","type":2,"name":"ROBOTICS;NOTES","name_cn":"机器人笔记","summary":"时代背景设定在世界变动率为“1.048596%”的2019年。在这样一个机器人已经普遍实用化的未来，种子岛中央高校的“机器人研究部”正面临废部危机，而仅有的两名部员之一——八汐海翔就算面临着这样的情况，仍旧对“机器人研究部”感到兴趣盎然，并且依旧热衷于机器人格斗游戏。而另一位一根筋的废材部长瀬乃宮秋穂为了避免被废部，正在以“完成巨型机器人”为目标奋斗着。然而某天，海翔发现了一份名为“君岛报告”的A.R.笔记。在这份笔记里面，记录着名为君岛安科的人将会把整个世界都卷进来的大阴谋。","eps":22,"eps_count":22,"air_date":"2012-10-11","air_weekday":4,"rating":{"total":2450,"count":{"1":5,"2":5,"3":17,"4":59,"5":166,"6":613,"7":885,"8":570,"9":94,"10":36},"score":6.8},"rank":2903,"images":{"large":"http://lain.bgm.tv/pic/cover/l/1c/4e/37673_HpP99.jpg","common":"http://lain.bgm.tv/pic/cover/c/1c/4e/37673_HpP99.jpg","medium":"http://lain.bgm.tv/pic/cover/m/1c/4e/37673_HpP99.jpg","small":"http://lain.bgm.tv/pic/cover/s/1c/4e/37673_HpP99.jpg","grid":"http://lain.bgm.tv/pic/cover/g/1c/4e/37673_HpP99.jpg"},"collection":{"wish":865,"collect":3017,"doing":466,"on_hold":387,"dropped":211}}