{"id":90612,"url":"http://bgm.tv/subject/90612","type":2,"name":"ピカチュウのわんぱくアイランド","name_cn":"精灵宝可梦：皮卡丘的顽皮岛","summary":"2006年に上映された作品","eps":1,"eps_count":1,"air_date":"2006-08-01","air_weekday":2,"rating":{"total":17,"count":{"1":0,"2":0,"3":0,"4":0,"5":4,"6":5,"7":4,"8":3,"9":1,"10":0},"score":6.5},"images":{"large":"http://lain.bgm.tv/pic/cover/l/33/44/90612_JW97H.jpg","common":"http://lain.bgm.tv/pic/cover/c/33/44/90612_JW97H.jpg","medium":"http://lain.bgm.tv/pic/cover/m/33/44/90612_JW97H.jpg","small":"http://lain.bgm.tv/pic/cover/s/33/44/90612_JW97H.jpg","grid":"http://lain.bgm.tv/pic/cover/g/33/44/90612_JW97H.jpg"},"collection":{"wish":9,"collect":38,"on_hold":1,"dropped":5}}