{"id":970,"url":"http://bgm.tv/subject/970","type":2,"name":"鉄のラインバレル","name_cn":"武装机甲","summary":"性格膽小怯懦的少年早瀨浩一，三年前在參觀正在建設的海上都市的建築工地時，遇上了意外事故。當時身受重傷瀕死的他，在昏迷了半年後醒來時，成了一個具有暴虐基因的好斗分子，而且身體里還獲得了未知的神秘力量……","eps":[{"id":1345,"url":"http://bgm.tv/ep/1345","type":0,"sort":1,"name":"クロガネと少年","name_cn":"","duration":"","airdate":"","comment":5,"desc":"","status":"Air"},{"id":1346,"url":"http://bgm.tv/ep/1346","type":0,"sort":2,"name":"疾走する正義","name_cn":"","duration":"","airdate":"","comment":0,"desc":"","status":"Air"},{"id":1347,"url":"http://bgm.tv/ep/1347","type":0,"sort":3,"name":"蒼の戦慄","name_cn":"","duration":"","airdate":"","comment":0,"desc":"","status":"Air"},{"id":1348,"url":"http://bgm.tv/ep/1348","type":0,"sort":4,"name":"正義の代償","name_cn":"","duration":"","airdate":"","comment":4,"desc":"","status":"Air"},{"id":1349,"url":"http://bgm.tv/ep/1349","type":0,"sort":5,"name":"明日への道標","name_cn":"","duration":"","airdate":"","comment":0,"desc":"","status":"Air"},{"id":1350,"url":"http://bgm.tv/ep/1350","type":0,"sort":6,"name":"明るい夜","name_cn":"","duration":"","airdate":"","comment":1,"desc":"","status":"Air"},{"id":1351,"url":"http://bgm.tv/ep/1351","type":0,"sort":7,"name":"サイアクな放課後","name_cn":"","duration":"","airdate":"","comment":1,"desc":"","status":"Air"},{"id":1352,"url":"http://bgm.tv/ep/1352","type":0,"sort":8,"name":"戯れの鬼たち","name_cn":"","duration":"","airdate":"","comment":1,"desc":"","status":"Air"},{"id":1353,"url":"http://bgm.tv/ep/1353","type":0,"sort":9,"name":"ブラック・チェンバー","name_cn":"","duration":"","airdate":"","comment":1,"desc":"","status":"Air"},{"id":1354,"url":"http://bgm.tv/ep/1354","type":0,"sort":10,"name":"OVER DRIVE","name_cn":"","duration":"","airdate":"","comment":0,"desc":"","status":"Air"},{"id":1355,"url":"http://bgm.tv/ep/1355","type":0,"sort":11,"name":"SUPER NOVA","name_cn":"","duration":"","airdate":"","comment":1,"desc":"","status":"Air"},{"id":1356,"url":"http://bgm.tv/ep/1356","type":0,"sort":12,"name":"南海より愛をこめて","name_cn":"","duration":"","airdate":"","comment":3,"desc":"","status":"Air"},{"id":1357,"url":"http://bgm.tv/ep/1357","type":0,"sort":13,"name":"黒の執行者","name_cn":"","duration":"","airdate":"","comment":1,"desc":"","status":"Air"},{"id":1358,"url":"http://bgm.tv/ep/1358","type":0,"sort":14,"name":"流れるは血、失うは涙","name_cn":"","duration":"","airdate":"","comment":0,"desc":"","status":"Air"},{"id":1359,"url":"http://bgm.tv/ep/1359","type":0,"sort":15,"name":"ベクトル","name_cn":"","duration":"","airdate":"","comment":1,"desc":"","status":"Air"},{"id":1360,"url":"http://bgm.tv/ep/1360","type":0,"sort":16,"name":"黄昏の断罪","name_cn":"","duration":"","airdate":"","comment":2,"desc":"","status":"Air"},{"id":1361,"url":"http://bgm.tv/ep/1361","type":0,"sort":17,"name":"機械じかけの呪い","name_cn":"","duration":"","airdate":"","comment":2,"desc":"","status":"Air"},{"id":1362,"url":"http://bgm.tv/ep/1362","type":0,"sort":18,"name":"メメント・モリ","name_cn":"","duration":"","airdate":"","comment":2,"desc":"","status":"Air"},{"id":1363,"url":"http://bgm.tv/ep/1363","type":0,"sort":19,"name":"届く陽、暴かれる陰","name_cn":"","duration":"","airdate":"","comment":1,"desc":"","status":"Air"},{"id":1364,"url":"http://bgm.tv/ep/1364","type":0,"sort":20,"name":"運命の男","name_cn":"","duration":"","airdate":"","comment":0,"desc":"","status":"Air"},{"id":1365,"url":"http://bgm.tv/ep/1365","type":0,"sort":21,"name":"狂気の翼","name_cn":"","duration":"","airdate":"","comment":2,"desc":"","status":"Air"},{"id":1366,"url":"http://bgm.tv/ep/1366","type":0,"sort":22,"name":"鬼を喰らうモノ","name_cn":"","duration":"","airdate":"","comment":1,"desc":"","status":"Air"},{"id":1367,"url":"http://bgm.tv/ep/1367","type":0,"sort":23,"name":"死に方が決める生き方","name_cn":"","duration":"","airdate":"","comment":2,"desc":"","status":"Air"},{"id":1368,"url":"http://bgm.tv/ep/1368","type":0,"sort":24,"name":"鋼鉄の華","name_cn":"","duration":"","airdate":"","comment":3,"desc":"","status":"Air"},{"id":24766,"url":"http://bgm.tv/ep/24766","type":0,"sort":25,"name":"天才美少女科学者レイチェルちゃん（TV未放映）","name_cn":"","duration":"","airdate":"","comment":2,"desc":"","status":"Air"},{"id":24767,"url":"http://bgm.tv/ep/24767","type":0,"sort":26,"name":"鉄の影（TV未放映）","name_cn":"","duration":"","airdate":"","comment":0,"desc":"","status":"Air"}],"eps_count":26,"air_date":"2008-10-03","air_weekday":5,"rating":{"total":380,"count":{"1":5,"2":8,"3":22,"4":47,"5":64,"6":104,"7":80,"8":37,"9":7,"10":6},"score":5.8},"rank":5422,"images":{"large":"http://lain.bgm.tv/pic/cover/l/89/fc/970_m4n5C.jpg","common":"http://lain.bgm.tv/pic/cover/c/89/fc/970_m4n5C.jpg","medium":"http://lain.bgm.tv/pic/cover/m/89/fc/970_m4n5C.jpg","small":"http://lain.bgm.tv/pic/cover/s/89/fc/970_m4n5C.jpg","grid":"http://lain.bgm.tv/pic/cover/g/89/fc/970_m4n5C.jpg"},"collection":{"wish":98,"collect":484,"doing":20,"on_hold":47,"dropped":80},"crt":[{"id":48551,"url":"http://bgm.tv/character/48551","name":"早瀬浩一","name_cn":"早濑浩一","role_name":"主角","images":{"large":"http://lain.bgm.tv/pic/crt/l/34/c1/48551_crt_Gj2HZ.jpg","medium":"http://lain.bgm.tv/pic/crt/m/34/c1/48551_crt_Gj2HZ.jpg","small":"http://lain.bgm.tv/pic/crt/s/34/c1/48551_crt_Gj2HZ.jpg","grid":"http://lain.bgm.tv/pic/crt/g/34/c1/48551_crt_Gj2HZ.jpg"},"comment":0,"collects":0,"info":{"name_cn":"早濑浩一","alias":{"jp":"早瀬 浩一","kana":"はやせ こういち","romaji":"Hayase Kouichi"},"gender":"男","birth":"2005年1月23日","bloodtype":"O型","height":"171cm","weight":"55kg"},"actors":[{"id":4782,"url":"http://bgm.tv/person/4782","name":"柿原徹也","images":{"large":"http://lain.bgm.tv/pic/crt/l/24/27/4782_prsn_51I79.jpg?r=1510051276","medium":"http://lain.bgm.tv/pic/crt/m/24/27/4782_prsn_51I79.jpg?r=1510051276","small":"http://lain.bgm.tv/pic/crt/s/24/27/4782_prsn_51I79.jpg?r=1510051276","grid":"http://lain.bgm.tv/pic/crt/g/24/27/4782_prsn_51I79.jpg?r=1510051276"}}]},{"id":2811,"url":"http://bgm.tv/character/2811","name":"石神邦生","name_cn":"","role_name":"配角","images":{"large":"http://lain.bgm.tv/pic/crt/l/22/7f/2811_crt_anidb.jpg","medium":"http://lain.bgm.tv/pic/crt/m/22/7f/2811_crt_anidb.jpg","small":"http://lain.bgm.tv/pic/crt/s/22/7f/2811_crt_anidb.jpg","grid":"http://lain.bgm.tv/pic/crt/g/22/7f/2811_crt_anidb.jpg"},"comment":0,"collects":0,"info":{"birth":"????-10-10","height":"186","weight":"70","gender":"男","alias":{"jp":"石神邦生","romaji":"Ishigami Kunio"},"source":"anidb.net"},"actors":[{"id":3971,"url":"http://bgm.tv/person/3971","name":"中田譲治","images":{"large":"http://lain.bgm.tv/pic/crt/l/7b/cb/3971_prsn_8ygm9.jpg?r=1518234792","medium":"http://lain.bgm.tv/pic/crt/m/7b/cb/3971_prsn_8ygm9.jpg?r=1518234792","small":"http://lain.bgm.tv/pic/crt/s/7b/cb/3971_prsn_8ygm9.jpg?r=1518234792","grid":"http://lain.bgm.tv/pic/crt/g/7b/cb/3971_prsn_8ygm9.jpg?r=1518234792"}}]},{"id":2813,"url":"http://bgm.tv/character/2813","name":"森次玲二","name_cn":"","role_name":"配角","images":{"large":"http://lain.bgm.tv/pic/crt/l/39/d3/2813_crt_anidb.jpg","medium":"http://lain.bgm.tv/pic/crt/m/39/d3/2813_crt_anidb.jpg","small":"http://lain.bgm.tv/pic/crt/s/39/d3/2813_crt_anidb.jpg","grid":"http://lain.bgm.tv/pic/crt/g/39/d3/2813_crt_anidb.jpg"},"comment":1,"collects":1,"info":{"birth":"1994-12-05","height":"185","weight":"65","gender":"男","alias":{"jp":"森次玲二","romaji":"Moritsugu Reiji"},"source":"anidb.net"},"actors":[{"id":4724,"url":"http://bgm.tv/person/4724","name":"中村悠一","images":{"large":"http://lain.bgm.tv/pic/crt/l/7a/78/4724_prsn_9RvRP.jpg?r=1589810155","medium":"http://lain.bgm.tv/pic/crt/m/7a/78/4724_prsn_9RvRP.jpg?r=1589810155","small":"http://lain.bgm.tv/pic/crt/s/7a/78/4724_prsn_9RvRP.jpg?r=1589810155","grid":"http://lain.bgm.tv/pic/crt/g/7a/78/4724_prsn_9RvRP.jpg?r=1589810155"}}]}],"staff":[{"id":3545,"url":"http://bgm.tv/person/3545","name":"清水栄一","name_cn":"清水荣一","role_name":"","images":null,"comment":0,"collects":0,"info":{"name_cn":"清水荣一","alias":{"kana":"しみず えいいち","romaji":"Shimizu Eiichi"},"gender":"男","birth":"1978-02-07"},"jobs":["原作"]},{"id":3544,"url":"http://bgm.tv/person/3544","name":"下口智裕","name_cn":"下口智裕","role_name":"","images":null,"comment":0,"collects":0,"info":{"name_cn":"下口智裕","alias":{"kana":"しもぐちともひろ","romaji":"Shimoguchi Tomohiro"},"gender":"男","birth":"1978年4月27日","bloodtype":"O型"},"jobs":["原作"]},{"id":777,"url":"http://bgm.tv/person/777","name":"日高政光","name_cn":"日高政光","role_name":"","images":{"large":"http://lain.bgm.tv/pic/crt/l/f1/c1/777_prsn_anidb.jpg","medium":"http://lain.bgm.tv/pic/crt/m/f1/c1/777_prsn_anidb.jpg","small":"http://lain.bgm.tv/pic/crt/s/f1/c1/777_prsn_anidb.jpg","grid":"http://lain.bgm.tv/pic/crt/g/f1/c1/777_prsn_anidb.jpg"},"comment":0,"collects":0,"info":{"name_cn":"日高政光","alias":{"0":"日高正光","kana":"ひだか まさみつ","romaji":"Hidaka Masamitsu"},"gender":"男","birth":"1960年10月19日"},"jobs":["导演","分镜"]},{"id":3546,"url":"http://bgm.tv/person/3546","name":"吉村清子","name_cn":"吉村清子","role_name":"","images":null,"comment":3,"collects":0,"info":{"name_cn":"吉村清子","alias":{"jp":"吉村清子","kana":"よしむら きよこ","romaji":"Yoshimura Kiyoko"},"gender":"女"},"jobs":["脚本"]},{"id":3663,"url":"http://bgm.tv/person/3663","name":"森田繁","name_cn":"森田繁","role_name":"","images":{"large":"http://lain.bgm.tv/pic/crt/l/1f/11/3663_prsn_9hU7Q.jpg","medium":"http://lain.bgm.tv/pic/crt/m/1f/11/3663_prsn_9hU7Q.jpg","small":"http://lain.bgm.tv/pic/crt/s/1f/11/3663_prsn_9hU7Q.jpg","grid":"http://lain.bgm.tv/pic/crt/g/1f/11/3663_prsn_9hU7Q.jpg"},"comment":1,"collects":0,"info":{"name_cn":"森田繁","alias":{"kana":"もりたしげる","romaji":"Morita Shigeru"},"gender":"男","birth":"1959年"},"jobs":["脚本"]},{"id":2718,"url":"http://bgm.tv/person/2718","name":"小野学","name_cn":"小野学","role_name":"","images":{"large":"http://lain.bgm.tv/pic/crt/l/77/87/2718_prsn_PW2wW.jpg?r=1489768180","medium":"http://lain.bgm.tv/pic/crt/m/77/87/2718_prsn_PW2wW.jpg?r=1489768180","small":"http://lain.bgm.tv/pic/crt/s/77/87/2718_prsn_PW2wW.jpg?r=1489768180","grid":"http://lain.bgm.tv/pic/crt/g/77/87/2718_prsn_PW2wW.jpg?r=1489768180"},"comment":52,"collects":0,"info":{"name_cn":"小野学","alias":{"jp":"小野学","kana":"おの まなぶ","romaji":"Ono Manabu"},"gender":"男"},"jobs":["分镜"]},{"id":1098,"url":"http://bgm.tv/person/1098","name":"柳沢テツヤ","name_cn":"柳泽哲也","role_name":"","images":null,"comment":5,"collects":0,"info":{"name_cn":"柳泽哲也","alias":{"0":"柳沢哲也","1":"大上相馬","jp":"柳沢テツヤ","kana":"やなぎさわ てつや","romaji":"Yanagisawa Tetsuya"},"gender":"男","birth":"5月28日"},"jobs":["分镜"]},{"id":15850,"url":"http://bgm.tv/person/15850","name":"吉沢俊一","name_cn":"吉泽俊一","role_name":"","images":null,"comment":0,"collects":0,"info":{"name_cn":"吉泽俊一"},"jobs":["分镜"]}],"topic":[{"id":3912,"url":"http://bgm.tv/subject/topic/3912","title":"桐岛英治如是说","main_id":970,"timestamp":1384667502,"lastpost":1384752926,"replies":2,"user":{"id":165527,"url":"http://bgm.tv/user/165527","username":"165527","nickname":"THOUSAND DRAGON小拳拳！！","avatar":{"large":"http://lain.bgm.tv/pic/user/l/000/16/55/165527.jpg?r=1605158312","medium":"http://lain.bgm.tv/pic/user/m/000/16/55/165527.jpg?r=1605158312","small":"http://lain.bgm.tv/pic/user/s/000/16/55/165527.jpg?r=1605158312"},"sign":null}},{"id":180,"url":"http://bgm.tv/subject/topic/180","title":"我说，在驾驶舱里是死不了的吧？","main_id":970,"timestamp":1237198279,"lastpost":1237784744,"replies":1,"user":{"id":271,"url":"http://bgm.tv/user/senken","username":"senken","nickname":"( ◕‿‿◕ )","avatar":{"large":"http://lain.bgm.tv/pic/user/l/000/00/02/271.jpg?r=1326294372","medium":"http://lain.bgm.tv/pic/user/m/000/00/02/271.jpg?r=1326294372","small":"http://lain.bgm.tv/pic/user/s/000/00/02/271.jpg?r=1326294372"},"sign":null}}],"blog":null}